bluerobotics_ping-0.2.2.data/scripts/omniscan450Example.py
bluerobotics_ping-0.2.2.data/scripts/ping1d-simulation.py
bluerobotics_ping-0.2.2.data/scripts/pingproxy.py
bluerobotics_ping-0.2.2.data/scripts/s500Example.py
bluerobotics_ping-0.2.2.data/scripts/simplePingExample.py
bluerobotics_ping-0.2.2.data/scripts/surveyor240Example.py
bluerobotics_ping-0.2.2.dist-info/licenses/LICENSE
brping/__init__.py
brping/definitions.py
brping/device.py
brping/omniscan450.py
brping/ping1d.py
brping/ping360.py
brping/pingmessage.py
brping/s500.py
brping/surveyor240.py
bluerobotics_ping-0.2.2.dist-info/METADATA
bluerobotics_ping-0.2.2.dist-info/WHEEL
bluerobotics_ping-0.2.2.dist-info/top_level.txt
bluerobotics_ping-0.2.2.dist-info/RECORD
