Metadata-Version: 2.4
Name: bluerobotics-ping
Version: 0.2.2
Summary: A python module for the Blue Robotics ping-protocol and products
Home-page: https://www.bluerobotics.com
Author: Blue Robotics
Author-email: support@bluerobotics.com
Classifier: Programming Language :: Python
Classifier: License :: OSI Approved :: MIT License
Classifier: Operating System :: OS Independent
Requires-Python: >=3.4
License-File: LICENSE
Requires-Dist: pyserial
Requires-Dist: future
Dynamic: author
Dynamic: author-email
Dynamic: classifier
Dynamic: description
Dynamic: description-content-type
Dynamic: home-page
Dynamic: license-file
Dynamic: requires-dist
Dynamic: requires-python
Dynamic: summary
